Stock_Analysys/__init__.py
Stock_Analysys/stockPredictor.py
stockpredictor-0.2.3.dist-info/METADATA
stockpredictor-0.2.3.dist-info/WHEEL
stockpredictor-0.2.3.dist-info/top_level.txt
stockpredictor-0.2.3.dist-info/RECORD
